CHANGELOG.md
LICENSE
README.md
lazy_env_configurator/__init__.py
lazy_env_configurator/custom_warnings.py
pytest.ini
requirements-test.txt
tox.ini
lazy_env_configurator-0.2.0.dist-info/LICENSE
lazy_env_configurator-0.2.0.dist-info/METADATA
lazy_env_configurator-0.2.0.dist-info/WHEEL
lazy_env_configurator-0.2.0.dist-info/RECORD
