Metadata-Version: 2.1
Name: lazy-env-configurator
Version: 0.2.0
Summary: Dynamic Config Class Creation using Environment Variables
Home-page: https://github.com/satyamsoni2211/lazy_env_configurator
License: MIT
Keywords: config,environment,variables,env,config,class,dynamic,creation,lazy-env-configurator,python
Author: satyam soni
Author-email: satyam.soni@hotmail.co.uk
Requires-Python: >=3.9,<4.0
Classifier: Framework :: Django
Classifier: Framework :: FastAPI
Classifier: Framework :: Flask
Classifier: License :: Freeware
Classifier: License :: OSI Approved :: MIT License
Classifier: Operating System :: OS Independent
Classifier: Programming Language :: Python :: 3
Classifier: Programming Language :: Python :: 3.9
Classifier: Programming Language :: Python :: 3.10
Classifier: Programming Language :: Python :: 3.11
Classifier: Programming Language :: Python :: 3.10
Classifier: Programming Language :: Python :: 3.11
Classifier: Programming Language :: Python :: 3.9
Classifier: Programming Language :: Python :: Implementation
Requires-Dist: python-dotenv (>=1.0.0,<2.0.0)
Project-URL: Repository, https://github.com/satyamsoni2211/lazy_env_configurator
